{"success": true, "data": [{"type": "correct", "challenge_id": 6, "challenge": {"name": "Finding Artifacts 1", "id": 6, "value": 50, "category": "osint"}, "user": {"name": "LMDS", "id": 1152}, "date": "2023-07-02T15:20:02.191411+00:00", "id": 27858, "team": {"name": "LMDS", "id": 650}}, {"type": "correct", "challenge_id": 9, "challenge": {"name": "Finding Jonah?", "id": 9, "value": 50, "category": "osint"}, "user": {"name": "LMDS", "id": 1152}, "date": "2023-07-02T02:14:59.235229+00:00", "id": 24163, "team": {"name": "LMDS", "id": 650}}, {"type": "correct", "challenge_id": 31, "challenge": {"name": "Chainmail", "id": 31, "value": 50, "category": "pwn"}, "user": {"name": "LMDS", "id": 1152}, "date": "2023-07-02T01:55:35.013070+00:00", "id": 24078, "team": {"name": "LMDS", "id": 650}}, {"type": "correct", "challenge_id": 7, "challenge": {"name": "Finding Artifacts 2", "id": 7, "value": 50, "category": "osint"}, "user": {"name": "LMDS", "id": 1152}, "date": "2023-07-02T01:32:27.109572+00:00", "id": 23882, "team": {"name": "LMDS", "id": 650}}, {"type": "correct", "challenge_id": 33, "challenge": {"name": "Join our Discord", "id": 33, "value": 1, "category": "misc"}, "user": {"name": "LMDS", "id": 1152}, "date": "2023-07-01T22:15:10.165772+00:00", "id": 22651, "team": {"name": "LMDS", "id": 650}}, {"type": "correct", "challenge_id": 18, "challenge": {"name": "At Home", "id": 18, "value": 50, "category": "crypto"}, "user": {"name": "LMDS", "id": 1152}, "date": "2023-07-01T21:44:59.588350+00:00", "id": 22409, "team": {"name": "LMDS", "id": 650}}, {"type": "correct", "challenge_id": 13, "challenge": {"name": "Three-Time Pad", "id": 13, "value": 50, "category": "crypto"}, "user": {"name": "LMDS", "id": 1152}, "date": "2023-07-01T21:43:05.995530+00:00", "id": 22385, "team": {"name": "LMDS", "id": 650}}, {"type": "correct", "challenge_id": 8, "challenge": {"name": "What's for Dinner?", "id": 8, "value": 50, "category": "osint"}, "user": {"name": "LMDS", "id": 1152}, "date": "2023-07-01T20:17:17.490951+00:00", "id": 21539, "team": {"name": "LMDS", "id": 650}}, {"type": "correct", "challenge_id": 3, "challenge": {"name": "vmwhere1", "id": 3, "value": 50, "category": "rev"}, "user": {"name": "LMDS", "id": 1152}, "date": "2023-07-01T14:30:54.838357+00:00", "id": 16820, "team": {"name": "LMDS", "id": 650}}, {"type": "correct", "challenge_id": 22, "challenge": {"name": "Corny Kernel", "id": 22, "value": 50, "category": "misc"}, "user": {"name": "LMDS", "id": 1152}, "date": "2023-07-01T13:01:43.291279+00:00", "id": 14966, "team": {"name": "LMDS", "id": 650}}], "meta": {"count": 10}}
