{"success": true, "data": [{"team": {"id": 1316, "name": "N00bz"}, "id": 29582, "user": {"id": 2462, "name": "Sqewly"}, "challenge_id": 33, "type": "correct", "date": "2023-07-02T22:00:14.062377+00:00", "challenge": {"id": 33, "category": "misc", "value": 1, "name": "Join our Discord"}}, {"team": {"id": 1316, "name": "N00bz"}, "id": 29567, "user": {"id": 2462, "name": "Sqewly"}, "challenge_id": 39, "type": "correct", "date": "2023-07-02T21:51:02.712076+00:00", "challenge": {"id": 39, "category": "misc", "value": 50, "name": "Feedback Survey"}}, {"team": {"id": 1316, "name": "N00bz"}, "id": 29548, "user": {"id": 2462, "name": "Sqewly"}, "challenge_id": 7, "type": "correct", "date": "2023-07-02T21:34:14.410949+00:00", "challenge": {"id": 7, "category": "osint", "value": 50, "name": "Finding Artifacts 2"}}], "meta": {"count": 3}}
