{"success": true, "data": [{"fields": [], "name": "supermeisty", "website": null, "team_id": 599, "affiliation": null, "id": 1036, "country": null, "oauth_id": null, "bracket": null, "points": 1}, {"fields": [], "name": "Hac", "website": null, "team_id": 599, "affiliation": null, "id": 1094, "country": null, "oauth_id": null, "bracket": null, "points": 0}, {"fields": [], "name": "lagman", "website": null, "team_id": 599, "affiliation": null, "id": 1101, "country": null, "oauth_id": null, "bracket": null, "points": 0}, {"fields": [], "name": "M3TR1C", "website": null, "team_id": 599, "affiliation": null, "id": 1236, "country": null, "oauth_id": null, "bracket": null, "points": 0}]}
