{"success": true, "data": [{"bracket": null, "affiliation": null, "oauth_id": null, "country": null, "name": "kleenex", "id": 447, "team_id": 258, "fields": [], "website": null, "points": 50}, {"bracket": null, "affiliation": null, "oauth_id": null, "country": "US", "name": "xMrRobotx", "id": 448, "team_id": 258, "fields": [], "website": "https://daishosec.com", "points": 250}, {"bracket": null, "affiliation": null, "oauth_id": null, "country": null, "name": "justinsomnia", "id": 449, "team_id": 258, "fields": [], "website": null, "points": 0}, {"bracket": null, "affiliation": null, "oauth_id": null, "country": null, "name": "INSOMNIAC TRACE : >", "id": 480, "team_id": 258, "fields": [], "website": "https://0xtrace.github.io/", "points": 498}, {"bracket": null, "affiliation": null, "oauth_id": null, "country": null, "name": "foxieon", "id": 1743, "team_id": 258, "fields": [], "website": null, "points": 101}, {"bracket": null, "affiliation": null, "oauth_id": null, "country": null, "name": "0xKJ", "id": 2082, "team_id": 258, "fields": [], "website": null, "points": 0}, {"bracket": null, "affiliation": null, "oauth_id": null, "country": null, "name": "sdushantha", "id": 2316, "team_id": 258, "fields": [], "website": null, "points": 0}]}
