{"success": true, "data": [{"team": {"id": 38, "name": "CyberTaskForce Zero"}, "id": 29334, "user": {"id": 62, "name": "CyberTaskForce Zero"}, "challenge_id": 12, "type": "correct", "date": "2023-07-02T20:26:56.493572+00:00", "challenge": {"id": 12, "category": "osint", "value": 50, "name": "First class mail"}}, {"team": {"id": 38, "name": "CyberTaskForce Zero"}, "id": 29252, "user": {"id": 62, "name": "CyberTaskForce Zero"}, "challenge_id": 39, "type": "correct", "date": "2023-07-02T20:10:07.265307+00:00", "challenge": {"id": 39, "category": "misc", "value": 50, "name": "Feedback Survey"}}, {"team": {"id": 38, "name": "CyberTaskForce Zero"}, "id": 29163, "user": {"id": 62, "name": "CyberTaskForce Zero"}, "challenge_id": 11, "type": "correct", "date": "2023-07-02T19:54:31.689634+00:00", "challenge": {"id": 11, "category": "osint", "value": 50, "name": "Jonah's Journal"}}, {"team": {"id": 38, "name": "CyberTaskForce Zero"}, "id": 29102, "user": {"id": 62, "name": "CyberTaskForce Zero"}, "challenge_id": 15, "type": "correct", "date": "2023-07-02T19:35:12.564412+00:00", "challenge": {"id": 15, "category": "pwn", "value": 127, "name": "Zapping a Setuid 1"}}, {"team": {"id": 38, "name": "CyberTaskForce Zero"}, "id": 27462, "user": {"id": 62, "name": "CyberTaskForce Zero"}, "challenge_id": 30, "type": "correct", "date": "2023-07-02T13:58:13.284929+00:00", "challenge": {"id": 30, "category": "web", "value": 99, "name": "peanut-xss"}}, {"team": {"id": 38, "name": "CyberTaskForce Zero"}, "id": 26897, "user": {"id": 62, "name": "CyberTaskForce Zero"}, "challenge_id": 10, "type": "correct", "date": "2023-07-02T12:29:30.187657+00:00", "challenge": {"id": 10, "category": "rev", "value": 181, "name": "geoguesser"}}, {"team": {"id": 38, "name": "CyberTaskForce Zero"}, "id": 21472, "user": {"id": 62, "name": "CyberTaskForce Zero"}, "challenge_id": 26, "type": "correct", "date": "2023-07-01T20:07:42.243855+00:00", "challenge": {"id": 26, "category": "rev", "value": 197, "name": "Fast Calculator"}}, {"team": {"id": 38, "name": "CyberTaskForce Zero"}, "id": 19798, "user": {"id": 62, "name": "CyberTaskForce Zero"}, "challenge_id": 22, "type": "correct", "date": "2023-07-01T17:53:49.804244+00:00", "challenge": {"id": 22, "category": "misc", "value": 50, "name": "Corny Kernel"}}, {"team": {"id": 38, "name": "CyberTaskForce Zero"}, "id": 19512, "user": {"id": 62, "name": "CyberTaskForce Zero"}, "challenge_id": 4, "type": "correct", "date": "2023-07-01T17:37:17.250401+00:00", "challenge": {"id": 4, "category": "rev", "value": 62, "name": "vmwhere2"}}, {"team": {"id": 38, "name": "CyberTaskForce Zero"}, "id": 19189, "user": {"id": 62, "name": "CyberTaskForce Zero"}, "challenge_id": 21, "type": "correct", "date": "2023-07-01T17:14:02.296149+00:00", "challenge": {"id": 21, "category": "crypto", "value": 50, "name": "Morphing Time"}}, {"team": {"id": 38, "name": "CyberTaskForce Zero"}, "id": 18801, "user": {"id": 62, "name": "CyberTaskForce Zero"}, "challenge_id": 20, "type": "correct", "date": "2023-07-01T16:40:01.819046+00:00", "challenge": {"id": 20, "category": "crypto", "value": 50, "name": "Group Project"}}, {"team": {"id": 38, "name": "CyberTaskForce Zero"}, "id": 18794, "user": {"id": 62, "name": "CyberTaskForce Zero"}, "challenge_id": 34, "type": "correct", "date": "2023-07-01T16:39:14.139346+00:00", "challenge": {"id": 34, "category": "crypto", "value": 50, "name": "Group Projection"}}, {"team": {"id": 38, "name": "CyberTaskForce Zero"}, "id": 18737, "user": {"id": 62, "name": "CyberTaskForce Zero"}, "challenge_id": 18, "type": "correct", "date": "2023-07-01T16:33:40.578320+00:00", "challenge": {"id": 18, "category": "crypto", "value": 50, "name": "At Home"}}, {"team": {"id": 38, "name": "CyberTaskForce Zero"}, "id": 18624, "user": {"id": 62, "name": "CyberTaskForce Zero"}, "challenge_id": 13, "type": "correct", "date": "2023-07-01T16:26:03.989718+00:00", "challenge": {"id": 13, "category": "crypto", "value": 50, "name": "Three-Time Pad"}}, {"team": {"id": 38, "name": "CyberTaskForce Zero"}, "id": 18420, "user": {"id": 62, "name": "CyberTaskForce Zero"}, "challenge_id": 31, "type": "correct", "date": "2023-07-01T16:13:19.993688+00:00", "challenge": {"id": 31, "category": "pwn", "value": 50, "name": "Chainmail"}}, {"team": {"id": 38, "name": "CyberTaskForce Zero"}, "id": 16584, "user": {"id": 62, "name": "CyberTaskForce Zero"}, "challenge_id": 3, "type": "correct", "date": "2023-07-01T14:17:21.000343+00:00", "challenge": {"id": 3, "category": "rev", "value": 50, "name": "vmwhere1"}}, {"team": {"id": 38, "name": "CyberTaskForce Zero"}, "id": 16249, "user": {"id": 62, "name": "CyberTaskForce Zero"}, "challenge_id": 9, "type": "correct", "date": "2023-07-01T13:58:50.557170+00:00", "challenge": {"id": 9, "category": "osint", "value": 50, "name": "Finding Jonah?"}}, {"team": {"id": 38, "name": "CyberTaskForce Zero"}, "id": 16044, "user": {"id": 62, "name": "CyberTaskForce Zero"}, "challenge_id": 8, "type": "correct", "date": "2023-07-01T13:48:31.330074+00:00", "challenge": {"id": 8, "category": "osint", "value": 50, "name": "What's for Dinner?"}}, {"team": {"id": 38, "name": "CyberTaskForce Zero"}, "id": 14747, "user": {"id": 62, "name": "CyberTaskForce Zero"}, "challenge_id": 7, "type": "correct", "date": "2023-07-01T12:46:27.537587+00:00", "challenge": {"id": 7, "category": "osint", "value": 50, "name": "Finding Artifacts 2"}}, {"team": {"id": 38, "name": "CyberTaskForce Zero"}, "id": 14698, "user": {"id": 62, "name": "CyberTaskForce Zero"}, "challenge_id": 6, "type": "correct", "date": "2023-07-01T12:42:24.558973+00:00", "challenge": {"id": 6, "category": "osint", "value": 50, "name": "Finding Artifacts 1"}}, {"team": {"id": 38, "name": "CyberTaskForce Zero"}, "id": 11931, "user": {"id": 62, "name": "CyberTaskForce Zero"}, "challenge_id": 33, "type": "correct", "date": "2023-07-01T10:07:53.386909+00:00", "challenge": {"id": 33, "category": "misc", "value": 1, "name": "Join our Discord"}}], "meta": {"count": 21}}
