{"success": true, "data": [{"type": "correct", "challenge_id": 27, "challenge": {"name": "futuredisk", "id": 27, "value": 332, "category": "web"}, "user": {"name": "imssm99", "id": 713}, "date": "2023-07-02T06:57:51.668290+00:00", "id": 25292, "team": {"name": "cat :flag_kr:", "id": 352}}, {"type": "correct", "challenge_id": 16, "challenge": {"name": "pwnykey", "id": 16, "value": 400, "category": "rev"}, "user": {"name": "D1N0", "id": 619}, "date": "2023-07-02T06:39:56.681436+00:00", "id": 25223, "team": {"name": "cat :flag_kr:", "id": 352}}, {"type": "correct", "challenge_id": 38, "challenge": {"name": "Schrodinger's Cat", "id": 38, "value": 381, "category": "misc"}, "user": {"name": "boo", "id": 727}, "date": "2023-07-02T04:42:13.455845+00:00", "id": 24765, "team": {"name": "cat :flag_kr:", "id": 352}}, {"type": "correct", "challenge_id": 10, "challenge": {"name": "geoguesser", "id": 10, "value": 181, "category": "rev"}, "user": {"name": "snwo", "id": 753}, "date": "2023-07-02T03:46:35.730174+00:00", "id": 24572, "team": {"name": "cat :flag_kr:", "id": 352}}, {"type": "correct", "challenge_id": 39, "challenge": {"name": "Feedback Survey", "id": 39, "value": 50, "category": "misc"}, "user": {"name": "1s0m0rph1sm", "id": 759}, "date": "2023-07-02T03:36:17.010099+00:00", "id": 24536, "team": {"name": "cat :flag_kr:", "id": 352}}, {"type": "correct", "challenge_id": 5, "challenge": {"name": "Tornado Warning", "id": 5, "value": 117, "category": "misc"}, "user": {"name": "boo", "id": 727}, "date": "2023-07-01T14:39:45.120369+00:00", "id": 16939, "team": {"name": "cat :flag_kr:", "id": 352}}, {"type": "correct", "challenge_id": 30, "challenge": {"name": "peanut-xss", "id": 30, "value": 99, "category": "web"}, "user": {"name": "imssm99", "id": 713}, "date": "2023-07-01T11:37:34.055598+00:00", "id": 13368, "team": {"name": "cat :flag_kr:", "id": 352}}, {"type": "correct", "challenge_id": 36, "challenge": {"name": "vimjail2.5", "id": 36, "value": 91, "category": "misc"}, "user": {"name": "D1N0", "id": 619}, "date": "2023-07-01T10:20:16.132271+00:00", "id": 12091, "team": {"name": "cat :flag_kr:", "id": 352}}, {"type": "correct", "challenge_id": 35, "challenge": {"name": "vimjail1.5", "id": 35, "value": 57, "category": "misc"}, "user": {"name": "D1N0", "id": 619}, "date": "2023-07-01T10:16:45.400736+00:00", "id": 12025, "team": {"name": "cat :flag_kr:", "id": 352}}, {"type": "correct", "challenge_id": 14, "challenge": {"name": "Virophage", "id": 14, "value": 301, "category": "pwn"}, "user": {"name": "wlswotmd", "id": 712}, "date": "2023-07-01T10:07:43.175129+00:00", "id": 11929, "team": {"name": "cat :flag_kr:", "id": 352}}, {"type": "correct", "challenge_id": 12, "challenge": {"name": "First class mail", "id": 12, "value": 50, "category": "osint"}, "user": {"name": "bww9641", "id": 1500}, "date": "2023-07-01T08:55:58.927526+00:00", "id": 10601, "team": {"name": "cat :flag_kr:", "id": 352}}, {"type": "correct", "challenge_id": 15, "challenge": {"name": "Zapping a Setuid 1", "id": 15, "value": 127, "category": "pwn"}, "user": {"name": "wlswotmd", "id": 712}, "date": "2023-07-01T08:25:12.675162+00:00", "id": 10276, "team": {"name": "cat :flag_kr:", "id": 352}}, {"type": "correct", "challenge_id": 11, "challenge": {"name": "Jonah's Journal", "id": 11, "value": 50, "category": "osint"}, "user": {"name": "D1N0", "id": 619}, "date": "2023-07-01T05:04:40.010789+00:00", "id": 7151, "team": {"name": "cat :flag_kr:", "id": 352}}, {"type": "correct", "challenge_id": 9, "challenge": {"name": "Finding Jonah?", "id": 9, "value": 50, "category": "osint"}, "user": {"name": "k_s", "id": 1262}, "date": "2023-07-01T04:42:43.667271+00:00", "id": 6818, "team": {"name": "cat :flag_kr:", "id": 352}}, {"type": "correct", "challenge_id": 34, "challenge": {"name": "Group Projection", "id": 34, "value": 50, "category": "crypto"}, "user": {"name": "1s0m0rph1sm", "id": 759}, "date": "2023-07-01T04:19:47.216613+00:00", "id": 6514, "team": {"name": "cat :flag_kr:", "id": 352}}, {"type": "correct", "challenge_id": 4, "challenge": {"name": "vmwhere2", "id": 4, "value": 62, "category": "rev"}, "user": {"name": "slyfizz", "id": 1266}, "date": "2023-07-01T03:54:07.874044+00:00", "id": 6064, "team": {"name": "cat :flag_kr:", "id": 352}}, {"type": "correct", "challenge_id": 8, "challenge": {"name": "What's for Dinner?", "id": 8, "value": 50, "category": "osint"}, "user": {"name": "D1N0", "id": 619}, "date": "2023-07-01T03:37:37.282888+00:00", "id": 5786, "team": {"name": "cat :flag_kr:", "id": 352}}, {"type": "correct", "challenge_id": 2, "challenge": {"name": "vimjail2", "id": 2, "value": 50, "category": "misc"}, "user": {"name": "D1N0", "id": 619}, "date": "2023-07-01T03:25:51.815895+00:00", "id": 5599, "team": {"name": "cat :flag_kr:", "id": 352}}, {"type": "correct", "challenge_id": 7, "challenge": {"name": "Finding Artifacts 2", "id": 7, "value": 50, "category": "osint"}, "user": {"name": "physicube", "id": 899}, "date": "2023-07-01T03:24:24.984286+00:00", "id": 5564, "team": {"name": "cat :flag_kr:", "id": 352}}, {"type": "correct", "challenge_id": 1, "challenge": {"name": "vimjail1", "id": 1, "value": 50, "category": "misc"}, "user": {"name": "D1N0", "id": 619}, "date": "2023-07-01T03:09:05.510427+00:00", "id": 5185, "team": {"name": "cat :flag_kr:", "id": 352}}, {"type": "correct", "challenge_id": 26, "challenge": {"name": "Fast Calculator", "id": 26, "value": 197, "category": "rev"}, "user": {"name": "snwo", "id": 753}, "date": "2023-07-01T02:27:40.016219+00:00", "id": 4266, "team": {"name": "cat :flag_kr:", "id": 352}}, {"type": "correct", "challenge_id": 6, "challenge": {"name": "Finding Artifacts 1", "id": 6, "value": 50, "category": "osint"}, "user": {"name": "sangjun", "id": 1379}, "date": "2023-07-01T02:08:42.573093+00:00", "id": 3844, "team": {"name": "cat :flag_kr:", "id": 352}}, {"type": "correct", "challenge_id": 22, "challenge": {"name": "Corny Kernel", "id": 22, "value": 50, "category": "misc"}, "user": {"name": "imssm99", "id": 713}, "date": "2023-07-01T01:48:36.062082+00:00", "id": 3172, "team": {"name": "cat :flag_kr:", "id": 352}}, {"type": "correct", "challenge_id": 3, "challenge": {"name": "vmwhere1", "id": 3, "value": 50, "category": "rev"}, "user": {"name": "slyfizz", "id": 1266}, "date": "2023-07-01T01:33:43.464355+00:00", "id": 2715, "team": {"name": "cat :flag_kr:", "id": 352}}, {"type": "correct", "challenge_id": 21, "challenge": {"name": "Morphing Time", "id": 21, "value": 50, "category": "crypto"}, "user": {"name": "ahpuh", "id": 876}, "date": "2023-07-01T00:43:35.460388+00:00", "id": 1051, "team": {"name": "cat :flag_kr:", "id": 352}}, {"type": "correct", "challenge_id": 33, "challenge": {"name": "Join our Discord", "id": 33, "value": 1, "category": "misc"}, "user": {"name": "ahpuh", "id": 876}, "date": "2023-07-01T00:34:38.224291+00:00", "id": 773, "team": {"name": "cat :flag_kr:", "id": 352}}, {"type": "correct", "challenge_id": 19, "challenge": {"name": "crack_the_safe", "id": 19, "value": 69, "category": "crypto"}, "user": {"name": "ahpuh", "id": 876}, "date": "2023-07-01T00:30:48.395545+00:00", "id": 665, "team": {"name": "cat :flag_kr:", "id": 352}}, {"type": "correct", "challenge_id": 20, "challenge": {"name": "Group Project", "id": 20, "value": 50, "category": "crypto"}, "user": {"name": "poro", "id": 711}, "date": "2023-07-01T00:28:17.279602+00:00", "id": 572, "team": {"name": "cat :flag_kr:", "id": 352}}, {"type": "correct", "challenge_id": 31, "challenge": {"name": "Chainmail", "id": 31, "value": 50, "category": "pwn"}, "user": {"name": "wlswotmd", "id": 712}, "date": "2023-07-01T00:21:03.358217+00:00", "id": 237, "team": {"name": "cat :flag_kr:", "id": 352}}, {"type": "correct", "challenge_id": 18, "challenge": {"name": "At Home", "id": 18, "value": 50, "category": "crypto"}, "user": {"name": "ahpuh", "id": 876}, "date": "2023-07-01T00:20:21.931478+00:00", "id": 217, "team": {"name": "cat :flag_kr:", "id": 352}}, {"type": "correct", "challenge_id": 13, "challenge": {"name": "Three-Time Pad", "id": 13, "value": 50, "category": "crypto"}, "user": {"name": "ahpuh", "id": 876}, "date": "2023-07-01T00:18:35.658735+00:00", "id": 169, "team": {"name": "cat :flag_kr:", "id": 352}}], "meta": {"count": 31}}
