{"success": true, "data": [{"user": 690, "description": "Hint for Finding Artifacts 2", "requirements": null, "category": "hints", "date": "2023-07-02T20:43:39.129120+00:00", "value": 0, "icon": null, "team": 154, "name": "Hint 309", "id": 2794, "team_id": 154, "type": "standard", "user_id": 690}, {"user": 690, "description": "Hint for Finding Artifacts 1", "requirements": null, "category": "hints", "date": "2023-07-02T20:43:22.579213+00:00", "value": 0, "icon": null, "team": 154, "name": "Hint 308", "id": 2793, "team_id": 154, "type": "standard", "user_id": 690}, {"user": 690, "description": "Hint for Finding Artifacts 1", "requirements": null, "category": "hints", "date": "2023-07-02T20:43:19.919026+00:00", "value": 0, "icon": null, "team": 154, "name": "Hint 307", "id": 2792, "team_id": 154, "type": "standard", "user_id": 690}, {"user": 690, "description": "Hint for Schrodinger's Cat", "requirements": null, "category": "hints", "date": "2023-07-02T20:34:28.826358+00:00", "value": 0, "icon": null, "team": 154, "name": "Hint 304", "id": 2791, "team_id": 154, "type": "standard", "user_id": 690}, {"user": 690, "description": "Hint for Schrodinger's Cat", "requirements": null, "category": "hints", "date": "2023-07-02T20:34:21.358507+00:00", "value": 0, "icon": null, "team": 154, "name": "Hint 303", "id": 2790, "team_id": 154, "type": "standard", "user_id": 690}, {"user": 690, "description": "Hint for First class mail", "requirements": null, "category": "hints", "date": "2023-07-02T19:37:56.760421+00:00", "value": 0, "icon": null, "team": 154, "name": "Hint 312", "id": 2764, "team_id": 154, "type": "standard", "user_id": 690}, {"user": 690, "description": "Hint for Finding Artifacts 1", "requirements": null, "category": "hints", "date": "2023-07-01T14:08:38.774934+00:00", "value": 0, "icon": null, "team": 154, "name": "Hint 263", "id": 1624, "team_id": 154, "type": "standard", "user_id": 690}, {"user": 261, "description": "Hint for Finding Jonah?", "requirements": null, "category": "hints", "date": "2023-07-01T03:10:25.594510+00:00", "value": 0, "icon": null, "team": 154, "name": "Hint 227", "id": 547, "team_id": 154, "type": "standard", "user_id": 261}, {"user": 261, "description": "Hint for Finding Artifacts 2", "requirements": null, "category": "hints", "date": "2023-07-01T02:35:58.661849+00:00", "value": 0, "icon": null, "team": 154, "name": "Hint 223", "id": 430, "team_id": 154, "type": "standard", "user_id": 261}], "meta": {"count": 9}}
