{"success": true, "data": [{"team": {"id": 916, "name": "\u6f22\u5821\u5305"}, "id": 10649, "user": {"id": 1694, "name": "doejohn"}, "challenge_id": 8, "type": "correct", "date": "2023-07-01T08:58:12.286172+00:00", "challenge": {"id": 8, "category": "osint", "value": 50, "name": "What's for Dinner?"}}, {"team": {"id": 916, "name": "\u6f22\u5821\u5305"}, "id": 10493, "user": {"id": 1694, "name": "doejohn"}, "challenge_id": 7, "type": "correct", "date": "2023-07-01T08:50:07.159120+00:00", "challenge": {"id": 7, "category": "osint", "value": 50, "name": "Finding Artifacts 2"}}], "meta": {"count": 2}}
