{"success": true, "data": [{"type": "correct", "challenge_id": 16, "challenge": {"name": "pwnykey", "id": 16, "value": 400, "category": "rev"}, "user": {"name": "Maple Bacon", "id": 298}, "date": "2023-07-03T00:14:51.076452+00:00", "id": 30155, "team": {"name": "Maple Bacon", "id": 174}}, {"type": "correct", "challenge_id": 30, "challenge": {"name": "peanut-xss", "id": 30, "value": 99, "category": "web"}, "user": {"name": "Maple Bacon", "id": 298}, "date": "2023-07-02T23:32:06.126886+00:00", "id": 29896, "team": {"name": "Maple Bacon", "id": 174}}, {"type": "correct", "challenge_id": 38, "challenge": {"name": "Schrodinger's Cat", "id": 38, "value": 381, "category": "misc"}, "user": {"name": "Maple Bacon", "id": 298}, "date": "2023-07-02T18:05:43.518218+00:00", "id": 28707, "team": {"name": "Maple Bacon", "id": 174}}, {"type": "correct", "challenge_id": 29, "challenge": {"name": "adminplz", "id": 29, "value": 322, "category": "web"}, "user": {"name": "Maple Bacon", "id": 298}, "date": "2023-07-02T09:35:51.774292+00:00", "id": 25940, "team": {"name": "Maple Bacon", "id": 174}}, {"type": "correct", "challenge_id": 39, "challenge": {"name": "Feedback Survey", "id": 39, "value": 50, "category": "misc"}, "user": {"name": "Maple Bacon", "id": 298}, "date": "2023-07-02T06:55:11.486841+00:00", "id": 25281, "team": {"name": "Maple Bacon", "id": 174}}, {"type": "correct", "challenge_id": 28, "challenge": {"name": "futuredisk2", "id": 28, "value": 457, "category": "web"}, "user": {"name": "Maple Bacon", "id": 298}, "date": "2023-07-02T06:30:21.296727+00:00", "id": 25179, "team": {"name": "Maple Bacon", "id": 174}}, {"type": "correct", "challenge_id": 4, "challenge": {"name": "vmwhere2", "id": 4, "value": 62, "category": "rev"}, "user": {"name": "Maple Bacon", "id": 298}, "date": "2023-07-02T03:58:41.585716+00:00", "id": 24656, "team": {"name": "Maple Bacon", "id": 174}}, {"type": "correct", "challenge_id": 37, "challenge": {"name": "Rattler Read", "id": 37, "value": 390, "category": "pwn"}, "user": {"name": "Maple Bacon", "id": 298}, "date": "2023-07-02T03:06:22.134805+00:00", "id": 24461, "team": {"name": "Maple Bacon", "id": 174}}, {"type": "correct", "challenge_id": 27, "challenge": {"name": "futuredisk", "id": 27, "value": 332, "category": "web"}, "user": {"name": "Maple Bacon", "id": 298}, "date": "2023-07-01T22:48:49.792829+00:00", "id": 22992, "team": {"name": "Maple Bacon", "id": 174}}, {"type": "correct", "challenge_id": 25, "challenge": {"name": "Mock Kernel", "id": 25, "value": 483, "category": "pwn"}, "user": {"name": "Maple Bacon", "id": 298}, "date": "2023-07-01T10:08:17.242660+00:00", "id": 11934, "team": {"name": "Maple Bacon", "id": 174}}, {"type": "correct", "challenge_id": 15, "challenge": {"name": "Zapping a Setuid 1", "id": 15, "value": 127, "category": "pwn"}, "user": {"name": "Maple Bacon", "id": 298}, "date": "2023-07-01T06:03:14.518924+00:00", "id": 8111, "team": {"name": "Maple Bacon", "id": 174}}, {"type": "correct", "challenge_id": 36, "challenge": {"name": "vimjail2.5", "id": 36, "value": 91, "category": "misc"}, "user": {"name": "Maple Bacon", "id": 298}, "date": "2023-07-01T05:49:33.975666+00:00", "id": 7921, "team": {"name": "Maple Bacon", "id": 174}}, {"type": "correct", "challenge_id": 35, "challenge": {"name": "vimjail1.5", "id": 35, "value": 57, "category": "misc"}, "user": {"name": "Maple Bacon", "id": 298}, "date": "2023-07-01T05:32:53.719740+00:00", "id": 7654, "team": {"name": "Maple Bacon", "id": 174}}, {"type": "correct", "challenge_id": 10, "challenge": {"name": "geoguesser", "id": 10, "value": 181, "category": "rev"}, "user": {"name": "Maple Bacon", "id": 298}, "date": "2023-07-01T04:22:49.681440+00:00", "id": 6569, "team": {"name": "Maple Bacon", "id": 174}}, {"type": "correct", "challenge_id": 34, "challenge": {"name": "Group Projection", "id": 34, "value": 50, "category": "crypto"}, "user": {"name": "Maple Bacon", "id": 298}, "date": "2023-07-01T04:16:47.061860+00:00", "id": 6464, "team": {"name": "Maple Bacon", "id": 174}}, {"type": "correct", "challenge_id": 3, "challenge": {"name": "vmwhere1", "id": 3, "value": 50, "category": "rev"}, "user": {"name": "Maple Bacon", "id": 298}, "date": "2023-07-01T03:53:55.973420+00:00", "id": 6060, "team": {"name": "Maple Bacon", "id": 174}}, {"type": "correct", "challenge_id": 2, "challenge": {"name": "vimjail2", "id": 2, "value": 50, "category": "misc"}, "user": {"name": "Maple Bacon", "id": 298}, "date": "2023-07-01T03:22:01.477747+00:00", "id": 5532, "team": {"name": "Maple Bacon", "id": 174}}, {"type": "correct", "challenge_id": 1, "challenge": {"name": "vimjail1", "id": 1, "value": 50, "category": "misc"}, "user": {"name": "Maple Bacon", "id": 298}, "date": "2023-07-01T03:12:33.421341+00:00", "id": 5274, "team": {"name": "Maple Bacon", "id": 174}}, {"type": "correct", "challenge_id": 12, "challenge": {"name": "First class mail", "id": 12, "value": 50, "category": "osint"}, "user": {"name": "Maple Bacon", "id": 298}, "date": "2023-07-01T02:16:23.499331+00:00", "id": 4051, "team": {"name": "Maple Bacon", "id": 174}}, {"type": "correct", "challenge_id": 5, "challenge": {"name": "Tornado Warning", "id": 5, "value": 117, "category": "misc"}, "user": {"name": "Maple Bacon", "id": 298}, "date": "2023-07-01T02:03:12.974888+00:00", "id": 3674, "team": {"name": "Maple Bacon", "id": 174}}, {"type": "correct", "challenge_id": 22, "challenge": {"name": "Corny Kernel", "id": 22, "value": 50, "category": "misc"}, "user": {"name": "Maple Bacon", "id": 298}, "date": "2023-07-01T01:46:37.032837+00:00", "id": 3118, "team": {"name": "Maple Bacon", "id": 174}}, {"type": "correct", "challenge_id": 19, "challenge": {"name": "crack_the_safe", "id": 19, "value": 69, "category": "crypto"}, "user": {"name": "Maple Bacon", "id": 298}, "date": "2023-07-01T01:23:45.321333+00:00", "id": 2486, "team": {"name": "Maple Bacon", "id": 174}}, {"type": "correct", "challenge_id": 11, "challenge": {"name": "Jonah's Journal", "id": 11, "value": 50, "category": "osint"}, "user": {"name": "Maple Bacon", "id": 298}, "date": "2023-07-01T01:12:38.731084+00:00", "id": 2166, "team": {"name": "Maple Bacon", "id": 174}}, {"type": "correct", "challenge_id": 21, "challenge": {"name": "Morphing Time", "id": 21, "value": 50, "category": "crypto"}, "user": {"name": "Maple Bacon", "id": 298}, "date": "2023-07-01T01:02:57.845698+00:00", "id": 1756, "team": {"name": "Maple Bacon", "id": 174}}, {"type": "correct", "challenge_id": 9, "challenge": {"name": "Finding Jonah?", "id": 9, "value": 50, "category": "osint"}, "user": {"name": "Maple Bacon", "id": 298}, "date": "2023-07-01T00:58:20.847738+00:00", "id": 1577, "team": {"name": "Maple Bacon", "id": 174}}, {"type": "correct", "challenge_id": 8, "challenge": {"name": "What's for Dinner?", "id": 8, "value": 50, "category": "osint"}, "user": {"name": "Maple Bacon", "id": 298}, "date": "2023-07-01T00:53:11.530675+00:00", "id": 1419, "team": {"name": "Maple Bacon", "id": 174}}, {"type": "correct", "challenge_id": 18, "challenge": {"name": "At Home", "id": 18, "value": 50, "category": "crypto"}, "user": {"name": "Maple Bacon", "id": 298}, "date": "2023-07-01T00:42:09.064383+00:00", "id": 993, "team": {"name": "Maple Bacon", "id": 174}}, {"type": "correct", "challenge_id": 20, "challenge": {"name": "Group Project", "id": 20, "value": 50, "category": "crypto"}, "user": {"name": "Maple Bacon", "id": 298}, "date": "2023-07-01T00:40:15.794557+00:00", "id": 929, "team": {"name": "Maple Bacon", "id": 174}}, {"type": "correct", "challenge_id": 7, "challenge": {"name": "Finding Artifacts 2", "id": 7, "value": 50, "category": "osint"}, "user": {"name": "Maple Bacon", "id": 298}, "date": "2023-07-01T00:36:16.565523+00:00", "id": 825, "team": {"name": "Maple Bacon", "id": 174}}, {"type": "correct", "challenge_id": 31, "challenge": {"name": "Chainmail", "id": 31, "value": 50, "category": "pwn"}, "user": {"name": "Maple Bacon", "id": 298}, "date": "2023-07-01T00:31:58.754099+00:00", "id": 703, "team": {"name": "Maple Bacon", "id": 174}}, {"type": "correct", "challenge_id": 6, "challenge": {"name": "Finding Artifacts 1", "id": 6, "value": 50, "category": "osint"}, "user": {"name": "Maple Bacon", "id": 298}, "date": "2023-07-01T00:31:51.831698+00:00", "id": 699, "team": {"name": "Maple Bacon", "id": 174}}, {"type": "correct", "challenge_id": 33, "challenge": {"name": "Join our Discord", "id": 33, "value": 1, "category": "misc"}, "user": {"name": "Maple Bacon", "id": 298}, "date": "2023-07-01T00:24:03.857341+00:00", "id": 350, "team": {"name": "Maple Bacon", "id": 174}}, {"type": "correct", "challenge_id": 13, "challenge": {"name": "Three-Time Pad", "id": 13, "value": 50, "category": "crypto"}, "user": {"name": "Maple Bacon", "id": 298}, "date": "2023-07-01T00:23:21.415173+00:00", "id": 321, "team": {"name": "Maple Bacon", "id": 174}}], "meta": {"count": 33}}
